amazon_sagemaker_jupyter_ai_q_developer/__init__.py
amazon_sagemaker_jupyter_ai_q_developer/_version.py
amazon_sagemaker_jupyter_ai_q_developer/constants.py
amazon_sagemaker_jupyter_ai_q_developer/exceptions.py
amazon_sagemaker_jupyter_ai_q_developer/extension.py
amazon_sagemaker_jupyter_ai_q_developer/file_cache_manager.py
amazon_sagemaker_jupyter_ai_q_developer/handlers.py
amazon_sagemaker_jupyter_ai_q_developer/llm.py
amazon_sagemaker_jupyter_ai_q_developer/provider.py
amazon_sagemaker_jupyter_ai_q_developer/request_logger.py
amazon_sagemaker_jupyter_ai_q_developer/sagemaker_client.py
amazon_sagemaker_jupyter_ai_q_developer/utils.py
amazon_sagemaker_jupyter_ai_q_developer/clients/base_client.py
amazon_sagemaker_jupyter_ai_q_developer/clients/q_dev_client.py
amazon_sagemaker_jupyter_ai_q_developer/clients/telemetry_client.py
amazon_sagemaker_jupyter_ai_q_developer/embeddings/codesage_embeddings.py
amazon_sagemaker_jupyter_ai_q_developer/embeddings/codesage_multiproc.py
amazon_sagemaker_jupyter_ai_q_developer/embeddings/codesage_provider.py
amazon_sagemaker_jupyter_ai_q_developer/embeddings/codesage/codesage-small/codesage-small-model.onnx.preprocessed.quantize_dynamic
amazon_sagemaker_jupyter_ai_q_developer/embeddings/codesage/codesage-small/tokenizer.json
amazon_sagemaker_jupyter_ai_q_developer/embeddings/codesage/codesage-small/tokenizer_config.json
amazon_sagemaker_jupyter_ai_q_developer/service_models/bearer/2022-11-11/service-2.json
amazon_sagemaker_jupyter_ai_q_developer/service_models/bearer/2023-11-27/service-2.json
amazon_sagemaker_jupyter_ai_q_developer/service_models/qdeveloperstreaming/2024-06-11/service-2.json
amazon_sagemaker_jupyter_ai_q_developer/slash_commands/ask.py
amazon_sagemaker_jupyter_ai_q_developer/slash_commands/base_streaming.py
amazon_sagemaker_jupyter_ai_q_developer/slash_commands/explain.py
amazon_sagemaker_jupyter_ai_q_developer/slash_commands/optimize.py
amazon_sagemaker_jupyter_ai_q_developer/slash_commands/refactor.py
amazon_sagemaker_jupyter_ai_q_developer-1.2.9.dist-info/METADATA
amazon_sagemaker_jupyter_ai_q_developer-1.2.9.dist-info/WHEEL
amazon_sagemaker_jupyter_ai_q_developer-1.2.9.dist-info/entry_points.txt
amazon_sagemaker_jupyter_ai_q_developer-1.2.9.dist-info/licenses/LICENSE
amazon_sagemaker_jupyter_ai_q_developer-1.2.9.dist-info/RECORD
