Metadata-Version: 2.4
Name: amazon_sagemaker_jupyter_ai_q_developer
Version: 1.2.9
Dynamic: Keywords
Summary: A JupyterLab extension.
Author: Amazon
License:                                 Apache License
License-File: LICENSE
Classifier: Framework :: Jupyter
Classifier: Framework :: Jupyter :: JupyterLab
Classifier: Framework :: Jupyter :: JupyterLab :: 4
Classifier: Framework :: Jupyter :: JupyterLab :: Extensions
Classifier: Framework :: Jupyter :: JupyterLab :: Extensions :: Prebuilt
Classifier: License :: OSI Approved :: BSD License
Classifier: Programming Language :: Python
Classifier: Programming Language :: Python :: 3
Classifier: Programming Language :: Python :: 3.8
Classifier: Programming Language :: Python :: 3.9
Classifier: Programming Language :: Python :: 3.10
Classifier: Programming Language :: Python :: 3.11
Classifier: Programming Language :: Python :: 3.12
Requires-Python: >=3.8
Requires-Dist: aws-embedded-metrics
Requires-Dist: boto3
Requires-Dist: botocore
Requires-Dist: ipython<9,>=8.33.0
Requires-Dist: jupyter-ai-magics<3,>=2.31.1
Requires-Dist: jupyter-ai<3,>=2.31.1
Requires-Dist: jupyter-server<3,>=2.0.1
Requires-Dist: langchain-core
Requires-Dist: numpy<=2.0.1
Requires-Dist: onnxruntime<2,>=1.15.0
Requires-Dist: pydantic<3,>=2.10.0
Requires-Dist: sagemaker-jupyterlab-extension-common<1,>=0.2.1
Requires-Dist: transformers<5,>=4.30.0
Provides-Extra: all
Requires-Dist: build; extra == 'all'
Requires-Dist: coverage; extra == 'all'
Requires-Dist: parameterized; extra == 'all'
Requires-Dist: pytest; extra == 'all'
Requires-Dist: pytest-asyncio; extra == 'all'
Requires-Dist: pytest-cov; extra == 'all'
Requires-Dist: pytest-jupyter[server]>=0.6.0; extra == 'all'
Requires-Dist: pytest-timeout; extra == 'all'
Requires-Dist: ruff; extra == 'all'
Requires-Dist: torch; extra == 'all'
Requires-Dist: twine; extra == 'all'
Provides-Extra: dev
Requires-Dist: build; extra == 'dev'
Requires-Dist: ruff; extra == 'dev'
Requires-Dist: twine; extra == 'dev'
Provides-Extra: test
Requires-Dist: coverage; extra == 'test'
Requires-Dist: parameterized; extra == 'test'
Requires-Dist: pytest; extra == 'test'
Requires-Dist: pytest-asyncio; extra == 'test'
Requires-Dist: pytest-cov; extra == 'test'
Requires-Dist: pytest-jupyter[server]>=0.6.0; extra == 'test'
Requires-Dist: pytest-timeout; extra == 'test'
Requires-Dist: torch; extra == 'test'
